percently-0.1.4.dist-info/METADATA
percently-0.1.4.dist-info/WHEEL
percently-0.1.4.dist-info/licenses/LICENSE
percently/__init__.py
percently/percently.cpython-312-darwin.so
percently-0.1.4.dist-info/RECORD
