Metadata-Version: 2.4
Name: percently
Version: 0.1.4
Classifier: Programming Language :: Rust
Classifier: Programming Language :: Python :: Implementation :: CPython
Classifier: Programming Language :: Python :: Implementation :: PyPy
License-File: LICENSE
Summary: A fast and efficient percentile calculator written in Rust.
Keywords: percentile,statistics,Rust,Python
Home-Page: https://github.com/4thel00z/percently
License-Expression: MIT
Requires-Python: >=3.9
